Metadata-Version: 2.1
Name: gaussian-theorems
Version: 1.1
Summary: Gaussian and Binomial distributions
Author: Makoha Dharren Pius
Author-email: dharrenpius@outlook.com
Classifier: Programming Language :: Python :: 3
Classifier: License :: OSI Approved :: MIT License
Classifier: Operating System :: OS Independent
Requires-Python: >=3.6
